setup.cfg
setup.py
lyricfool/__init__.py
lyricfool/adapters.py
lyricfool/app.py
lyricfool/tests.py
lyricfool.egg-info/PKG-INFO
lyricfool.egg-info/SOURCES.txt
lyricfool.egg-info/dependency_links.txt
lyricfool.egg-info/entry_points.txt
lyricfool.egg-info/requires.txt
lyricfool.egg-info/top_level.txt