Metadata-Version: 1.0
Name: lyricfool
Version: 0.1.1
Summary: lyricfool
Home-page: http://github.com/miciaiahparker/lyricfool
Author: Micaiah Parker
Author-email: me@micaiahparker.com
License: MIT
Platform: UNKNOWN
